mfd_powermanagement/__init__.py
mfd_powermanagement/base.py
mfd_powermanagement/ccsg.py
mfd_powermanagement/data_structures.py
mfd_powermanagement/dli.py
mfd_powermanagement/exceptions.py
mfd_powermanagement/ipmi.py
mfd_powermanagement/pdu.py
mfd_powermanagement/consts/__init__.py
mfd_powermanagement/consts/ccsg.py
mfd_powermanagement/system/__init__.py
mfd_powermanagement/system/base.py
mfd_powermanagement/system/freebsd.py
mfd_powermanagement/system/linux.py
mfd_powermanagement/system/windows.py
mfd_powermanagement-1.12.1.dist-info/licenses/AUTHORS.md
mfd_powermanagement-1.12.1.dist-info/licenses/LICENSE.md
mfd_powermanagement-1.12.1.dist-info/METADATA
mfd_powermanagement-1.12.1.dist-info/WHEEL
mfd_powermanagement-1.12.1.dist-info/top_level.txt
mfd_powermanagement-1.12.1.dist-info/RECORD
