Metadata-Version: 2.4
Name: mfd-powermanagement
Version: 1.12.1
Summary: Module for managing power (Raritan, APC, Digital Loggers, ipmi, etc.)
Project-URL: Homepage, https://github.com/intel/mfd
Project-URL: Repository, https://github.com/intel/mfd-powermanagement
Project-URL: Issues, https://github.com/intel/mfd-powermanagement/issues
Project-URL: Changelog, https://github.com/intel/mfd-powermanagement/blob/main/CHANGELOG.md
Requires-Python: <3.14,>=3.10
License-File: LICENSE.md
License-File: AUTHORS.md
Requires-Dist: dlipower>=1.0
Requires-Dist: pyasn1==0.4.8
Requires-Dist: pysnmp~=7.1.20
Requires-Dist: requests<3,>=2.27
Requires-Dist: mfd_connect>=7.12.0
Requires-Dist: mfd-common-libs>=1.11.0
Dynamic: license-file
